bigyo/__init__.py
bigyo/_bigyo.py
bigyo/bigyo_renderer/__init__.py
bigyo/bigyo_renderer/_bigyo_renderer.py
bigyo-1.0.0.dist-info/LICENSE
bigyo-1.0.0.dist-info/METADATA
bigyo-1.0.0.dist-info/WHEEL
bigyo-1.0.0.dist-info/top_level.txt
bigyo-1.0.0.dist-info/RECORD
