Metadata-Version: 2.1
Name: bigyo
Version: 1.0.0
Summary: Python library for side-by-side diff in terminal, use difflib as its engine. Supports beautiful output with multi-width or zero-width character.
Author-email: LegenDUST <dhnam0502@naver.com>
License: MIT License
Project-URL: repository, https://github.com/dhnam/bigyo
Classifier: Programming Language :: Python :: 3
Classifier: License :: OSI Approved :: MIT License
Classifier: Operating System :: OS Independent
Requires-Python: >=3.6
License-File: LICENSE
Requires-Dist: wcwidth
